README.txt
setup.py
django_resourcetags/__init__.py
django_resourcetags/genshi_integration.py
django_resourcetags/handlers.py
django_resourcetags/resource_factory.py
django_resourcetags/util.py
django_resourcetags.egg-info/PKG-INFO
django_resourcetags.egg-info/SOURCES.txt
django_resourcetags.egg-info/dependency_links.txt
django_resourcetags.egg-info/requires.txt
django_resourcetags.egg-info/top_level.txt
django_resourcetags/compression/__init__.py
django_resourcetags/compression/css_filter.py
django_resourcetags/compression/filters.py
django_resourcetags/compression/jsmin.py
django_resourcetags/management/__init__.py
django_resourcetags/management/commands/__init__.py
django_resourcetags/management/commands/compressresources.py
django_resourcetags/templatetags/__init__.py
django_resourcetags/templatetags/resources.py
django_resourcetags/tests/__init__.py
django_resourcetags/tests/mocking.py
django_resourcetags/tests/settings.py
django_resourcetags/tests/test_compression.py
django_resourcetags/tests/test_genshi_integration.py
django_resourcetags/tests/test_handlers.py
django_resourcetags/tests/test_resource_factory.py
django_resourcetags/tests/test_templatetags.py