Metadata-Version: 1.0
Name: django-resourcetags
Version: 1.1
Summary: Django template tags for referencing static files
Home-page: https://launchpad.net/django-resourcetags
Author: John Millikin
Author-email: jmillikin@gmail.com
License: GPL
Download-URL: http://pypi.python.org/pypi/django-resourcetags/1.1
Keywords: django
Platform: Platform Independent
Classifier: Development Status :: 4 - Beta
Classifier: Framework :: Django
Classifier: Intended Audience :: Developers
Classifier: License :: OSI Approved :: GNU General Public License (GPL)
Classifier: Operating System :: OS Independent
Classifier: Programming Language :: Python
Classifier: Topic :: Internet :: WWW/HTTP :: Dynamic Content
Classifier: Topic :: Software Development :: Libraries :: Python Modules
